takopi_discord/__init__.py
takopi_discord/backend.py
takopi_discord/bridge.py
takopi_discord/client.py
takopi_discord/file_transfer.py
takopi_discord/handlers.py
takopi_discord/loop.py
takopi_discord/mapping.py
takopi_discord/onboarding.py
takopi_discord/outbox.py
takopi_discord/overrides.py
takopi_discord/render.py
takopi_discord/state.py
takopi_discord/types.py
takopi_discord/voice.py
takopi_discord/commands/__init__.py
takopi_discord/commands/dispatch.py
takopi_discord/commands/executor.py
takopi_discord/commands/registration.py
takopi_discord-0.3.0.dist-info/METADATA
takopi_discord-0.3.0.dist-info/WHEEL
takopi_discord-0.3.0.dist-info/entry_points.txt
takopi_discord-0.3.0.dist-info/RECORD
