Metadata-Version: 2.4
Name: takopi-discord
Version: 0.3.0
Summary: Discord transport plugin for takopi
Project-URL: Homepage, https://github.com/asianviking/takopi-discord
Project-URL: Repository, https://github.com/asianviking/takopi-discord
Project-URL: Issues, https://github.com/asianviking/takopi-discord/issues
Author: ayvee
License: MIT
Classifier: License :: OSI Approved :: MIT License
Classifier: Operating System :: OS Independent
Classifier: Programming Language :: Python :: 3
Classifier: Programming Language :: Python :: 3 :: Only
Classifier: Programming Language :: Python :: 3.14
Requires-Python: >=3.14
Requires-Dist: openai>=1.0.0
Requires-Dist: py-cord>=2.6.0
Requires-Dist: pywhispercpp>=1.4.0
Requires-Dist: takopi>=0.17.0
